cgai_io/Copy.py
cgai_io/Delete.py
cgai_io/Info.py
cgai_io/Move.py
cgai_io/Name.py
cgai_io/Pack.py
cgai_io/__init__.py
cgai_io/_util.py
cgai_io-1.2.0.dist-info/LICENSE
cgai_io-1.2.0.dist-info/METADATA
cgai_io-1.2.0.dist-info/WHEEL
cgai_io-1.2.0.dist-info/top_level.txt
cgai_io-1.2.0.dist-info/RECORD
